{"ticker": "EQR", "ohlc": [{"time": "2024-11-15", "open": 69.13, "high": 70.14, "low": 68.92, "close": 69.93, "rsi": 45.5}, {"time": "2024-11-18", "open": 69.66, "high": 70.83, "low": 69.51, "close": 70.72, "rsi": 50.6}, {"time": "2024-11-19", "open": 70.33, "high": 70.96, "low": 69.93, "close": 70.79, "rsi": 51.8}, {"time": "2024-11-20", "open": 70.43, "high": 70.53, "low": 69.73, "close": 70.24, "rsi": 64.1}, {"time": "2024-11-21", "open": 70.46, "high": 71.53, "low": 70.2, "close": 71.32, "rsi": 73.7}, {"time": "2024-11-22", "open": 71.37, "high": 72.47, "low": 71.04, "close": 72.02, "rsi": 73.0}, {"time": "2024-11-25", "open": 72.73, "high": 73.38, "low": 72.47, "close": 72.61, "rsi": 70.0}, {"time": "2024-11-26", "open": 72.7, "high": 73.51, "low": 72.58, "close": 73.26, "rsi": 76.0}, {"time": "2024-11-27", "open": 73.94, "high": 74.42, "low": 73.46, "close": 73.62, "rsi": 76.0}, {"time": "2024-11-29", "open": 73.61, "high": 73.88, "low": 72.78, "close": 72.85, "rsi": 65.6}, {"time": "2024-12-02", "open": 72.38, "high": 72.59, "low": 71.19, "close": 71.5, "rsi": 57.6}, {"time": "2024-12-03", "open": 71.56, "high": 71.71, "low": 70.33, "close": 70.35, "rsi": 54.0}, {"time": "2024-12-04", "open": 70.4, "high": 70.5, "low": 69.83, "close": 70.12, "rsi": 46.1}, {"time": "2024-12-05", "open": 69.61, "high": 69.98, "low": 69.27, "close": 69.73, "rsi": 51.6}, {"time": "2024-12-06", "open": 69.96, "high": 70.29, "low": 69.58, "close": 70.08, "rsi": 50.8}, {"time": "2024-12-09", "open": 70.02, "high": 70.23, "low": 69.21, "close": 69.99, "rsi": 45.7}, {"time": "2024-12-10", "open": 70.17, "high": 70.17, "low": 69.14, "close": 69.27, "rsi": 41.5}, {"time": "2024-12-11", "open": 69.49, "high": 69.77, "low": 68.9, "close": 69.16, "rsi": 43.7}, {"time": "2024-12-12", "open": 69.11, "high": 70.69, "low": 69.03, "close": 70.12, "rsi": 42.9}, {"time": "2024-12-13", "open": 69.78, "high": 70.34, "low": 69.32, "close": 69.63, "rsi": 35.5}, {"time": "2024-12-16", "open": 69.54, "high": 70.67, "low": 69.48, "close": 69.8, "rsi": 32.0}, {"time": "2024-12-17", "open": 69.51, "high": 69.93, "low": 69.11, "close": 69.15, "rsi": 23.6}, {"time": "2024-12-18", "open": 68.89, "high": 69.57, "low": 66.66, "close": 66.7, "rsi": 15.0}, {"time": "2024-12-19", "open": 66.83, "high": 67.84, "low": 65.9, "close": 66.03, "rsi": 15.2}, {"time": "2024-12-20", "open": 67.01, "high": 68.53, "low": 66.46, "close": 67.8, "rsi": 31.9}, {"time": "2024-12-23", "open": 67.23, "high": 68.05, "low": 67.0, "close": 67.89, "rsi": 36.5}, {"time": "2024-12-24", "open": 67.68, "high": 68.74, "low": 67.53, "close": 68.63, "rsi": 42.3}, {"time": "2024-12-26", "open": 68.46, "high": 68.94, "low": 68.23, "close": 68.77, "rsi": 44.9}, {"time": "2024-12-27", "open": 68.15, "high": 69.04, "low": 67.86, "close": 68.02, "rsi": 39.5}, {"time": "2024-12-30", "open": 67.63, "high": 67.87, "low": 66.83, "close": 67.62, "rsi": 38.3}, {"time": "2024-12-31", "open": 68.34, "high": 68.38, "low": 67.37, "close": 68.19, "rsi": 44.6}, {"time": "2025-01-02", "open": 67.87, "high": 68.42, "low": 67.02, "close": 67.22, "rsi": 41.0}, {"time": "2025-01-03", "open": 67.07, "high": 68.08, "low": 66.98, "close": 68.01, "rsi": 40.1}, {"time": "2025-01-06", "open": 67.76, "high": 68.13, "low": 65.55, "close": 65.6, "rsi": 34.0}, {"time": "2025-01-07", "open": 65.97, "high": 66.26, "low": 64.44, "close": 64.7, "rsi": 30.8}, {"time": "2025-01-08", "open": 64.83, "high": 64.91, "low": 63.95, "close": 64.77, "rsi": 32.8}, {"time": "2025-01-10", "open": 64.41, "high": 65.23, "low": 63.93, "close": 64.25, "rsi": 38.7}, {"time": "2025-01-13", "open": 64.46, "high": 66.56, "low": 64.27, "close": 66.39, "rsi": 51.5}, {"time": "2025-01-14", "open": 66.52, "high": 67.25, "low": 66.08, "close": 67.07, "rsi": 46.7}, {"time": "2025-01-15", "open": 68.72, "high": 69.07, "low": 66.58, "close": 66.63, "rsi": 44.6}, {"time": "2025-01-16", "open": 66.84, "high": 67.46, "low": 66.29, "close": 67.39, "rsi": 44.6}, {"time": "2025-01-17", "open": 67.08, "high": 67.67, "low": 66.74, "close": 66.93, "rsi": 42.2}, {"time": "2025-01-21", "open": 67.03, "high": 67.79, "low": 66.73, "close": 67.27, "rsi": 46.7}, {"time": "2025-01-22", "open": 66.68, "high": 66.83, "low": 65.46, "close": 65.59, "rsi": 42.1}, {"time": "2025-01-23", "open": 65.76, "high": 66.05, "low": 64.96, "close": 65.41, "rsi": 38.8}, {"time": "2025-01-24", "open": 65.15, "high": 65.94, "low": 65.05, "close": 65.47, "rsi": 42.4}, {"time": "2025-01-27", "open": 65.59, "high": 67.54, "low": 65.37, "close": 67.28, "rsi": 47.1}, {"time": "2025-01-28", "open": 67.17, "high": 67.49, "low": 66.25, "close": 66.44, "rsi": 53.8}, {"time": "2025-01-29", "open": 66.45, "high": 66.93, "low": 65.51, "close": 65.69, "rsi": 54.6}, {"time": "2025-01-30", "open": 66.74, "high": 67.58, "low": 66.43, "close": 66.9, "rsi": 59.0}, {"time": "2025-01-31", "open": 66.86, "high": 68.06, "low": 66.6, "close": 67.75, "rsi": 64.3}, {"time": "2025-02-03", "open": 67.23, "high": 67.78, "low": 66.28, "close": 67.47, "rsi": 55.2}, {"time": "2025-02-04", "open": 67.63, "high": 68.48, "low": 66.29, "close": 67.74, "rsi": 53.4}, {"time": "2025-02-05", "open": 68.31, "high": 69.35, "low": 67.84, "close": 69.0, "rsi": 61.0}, {"time": "2025-02-06", "open": 69.27, "high": 69.61, "low": 68.79, "close": 69.18, "rsi": 58.8}, {"time": "2025-02-07", "open": 69.33, "high": 69.49, "low": 68.07, "close": 68.42, "rsi": 57.1}, {"time": "2025-02-10", "open": 68.29, "high": 68.32, "low": 67.12, "close": 68.02, "rsi": 53.5}, {"time": "2025-02-11", "open": 67.53, "high": 68.57, "low": 67.47, "close": 68.53, "rsi": 65.6}, {"time": "2025-02-12", "open": 67.33, "high": 68.59, "low": 67.24, "close": 68.08, "rsi": 63.8}, {"time": "2025-02-13", "open": 68.06, "high": 68.83, "low": 67.9, "close": 68.61, "rsi": 65.5}, {"time": "2025-02-14", "open": 68.97, "high": 69.57, "low": 68.32, "close": 68.33, "rsi": 56.1}, {"time": "2025-02-18", "open": 68.15, "high": 68.71, "low": 67.66, "close": 68.36, "rsi": 62.3}, {"time": "2025-02-19", "open": 68.07, "high": 68.48, "low": 67.66, "close": 68.22, "rsi": 67.7}, {"time": "2025-02-20", "open": 68.16, "high": 68.97, "low": 67.83, "close": 68.74, "rsi": 64.2}, {"time": "2025-02-21", "open": 68.78, "high": 69.0, "low": 67.99, "close": 68.65, "rsi": 57.8}, {"time": "2025-02-24", "open": 68.75, "high": 69.73, "low": 68.4, "close": 69.27, "rsi": 64.9}, {"time": "2025-02-25", "open": 69.49, "high": 70.57, "low": 69.49, "close": 70.01, "rsi": 67.4}, {"time": "2025-02-26", "open": 70.0, "high": 70.58, "low": 69.65, "close": 69.85, "rsi": 57.9}, {"time": "2025-02-27", "open": 69.66, "high": 71.36, "low": 69.58, "close": 70.68, "rsi": 62.4}, {"time": "2025-02-28", "open": 71.25, "high": 71.87, "low": 70.23, "close": 71.15, "rsi": 73.7}, {"time": "2025-03-03", "open": 71.15, "high": 72.54, "low": 70.78, "close": 71.96, "rsi": 82.0}, {"time": "2025-03-04", "open": 72.23, "high": 72.77, "low": 70.42, "close": 70.45, "rsi": 63.4}, {"time": "2025-03-05", "open": 69.71, "high": 70.9, "low": 69.27, "close": 70.67, "rsi": 68.6}, {"time": "2025-03-06", "open": 70.11, "high": 70.18, "low": 68.46, "close": 68.98, "rsi": 52.3}, {"time": "2025-03-07", "open": 69.2, "high": 69.76, "low": 68.47, "close": 69.04, "rsi": 54.5}, {"time": "2025-03-10", "open": 69.17, "high": 70.16, "low": 67.74, "close": 67.99, "rsi": 48.0}, {"time": "2025-03-11", "open": 68.3, "high": 68.43, "low": 66.39, "close": 66.94, "rsi": 43.5}, {"time": "2025-03-12", "open": 66.78, "high": 67.13, "low": 65.96, "close": 66.16, "rsi": 37.2}, {"time": "2025-03-13", "open": 66.16, "high": 66.84, "low": 65.36, "close": 65.5, "rsi": 35.2}, {"time": "2025-03-14", "open": 65.74, "high": 66.16, "low": 65.0, "close": 66.13, "rsi": 35.3}, {"time": "2025-03-17", "open": 65.91, "high": 67.73, "low": 65.91, "close": 67.21, "rsi": 37.3}, {"time": "2025-03-18", "open": 67.03, "high": 67.53, "low": 66.29, "close": 66.68, "rsi": 36.0}, {"time": "2025-03-19", "open": 66.48, "high": 67.25, "low": 66.0, "close": 66.93, "rsi": 32.6}, {"time": "2025-03-20", "open": 67.06, "high": 67.52, "low": 66.4, "close": 67.31, "rsi": 32.1}, {"time": "2025-03-21", "open": 67.0, "high": 67.33, "low": 66.11, "close": 66.97, "rsi": 25.6}, {"time": "2025-03-24", "open": 67.26, "high": 68.64, "low": 67.05, "close": 68.45, "rsi": 40.2}, {"time": "2025-03-25", "open": 68.51, "high": 69.23, "low": 67.56, "close": 68.14, "rsi": 37.7}, {"time": "2025-03-26", "open": 68.65, "high": 68.96, "low": 68.15, "close": 68.65, "rsi": 48.2}, {"time": "2025-03-27", "open": 68.81, "high": 69.69, "low": 68.23, "close": 68.36, "rsi": 46.4}, {"time": "2025-03-28", "open": 68.88, "high": 68.88, "low": 67.86, "close": 68.47, "rsi": 52.8}, {"time": "2025-03-31", "open": 68.93, "high": 69.84, "low": 68.67, "close": 69.34, "rsi": 64.5}, {"time": "2025-04-01", "open": 69.34, "high": 69.71, "low": 68.24, "close": 69.05, "rsi": 68.6}, {"time": "2025-04-02", "open": 68.64, "high": 69.72, "low": 68.39, "close": 69.39, "rsi": 76.1}, {"time": "2025-04-03", "open": 68.75, "high": 69.3, "low": 66.1, "close": 66.4, "rsi": 51.4}, {"time": "2025-04-04", "open": 65.51, "high": 66.06, "low": 61.64, "close": 61.79, "rsi": 29.7}, {"time": "2025-04-07", "open": 60.76, "high": 62.77, "low": 58.78, "close": 60.56, "rsi": 28.2}, {"time": "2025-04-08", "open": 62.35, "high": 62.35, "low": 59.0, "close": 59.88, "rsi": 25.6}, {"time": "2025-04-09", "open": 58.71, "high": 65.36, "low": 57.55, "close": 64.77, "rsi": 43.3}, {"time": "2025-04-10", "open": 63.59, "high": 64.89, "low": 60.58, "close": 62.26, "rsi": 38.9}, {"time": "2025-04-11", "open": 61.9, "high": 63.19, "low": 60.32, "close": 62.61, "rsi": 35.4}, {"time": "2025-04-14", "open": 63.27, "high": 65.25, "low": 63.1, "close": 64.82, "rsi": 42.4}, {"time": "2025-04-15", "open": 65.08, "high": 65.36, "low": 64.36, "close": 64.92, "rsi": 41.3}, {"time": "2025-04-16", "open": 64.78, "high": 65.81, "low": 64.56, "close": 64.95, "rsi": 42.0}, {"time": "2025-04-17", "open": 65.01, "high": 67.07, "low": 64.94, "close": 66.1, "rsi": 44.7}, {"time": "2025-04-21", "open": 65.52, "high": 65.95, "low": 64.44, "close": 65.39, "rsi": 41.1}, {"time": "2025-04-22", "open": 66.32, "high": 67.1, "low": 65.95, "close": 66.77, "rsi": 45.1}, {"time": "2025-04-23", "open": 67.37, "high": 68.43, "low": 66.72, "close": 67.21, "rsi": 45.3}, {"time": "2025-04-24", "open": 67.07, "high": 67.55, "low": 66.63, "close": 67.14, "rsi": 51.8}, {"time": "2025-04-25", "open": 66.94, "high": 67.13, "low": 66.22, "close": 66.38, "rsi": 63.9}, {"time": "2025-04-28", "open": 66.42, "high": 67.27, "low": 66.31, "close": 67.14, "rsi": 70.5}, {"time": "2025-04-29", "open": 66.78, "high": 67.68, "low": 66.17, "close": 67.35, "rsi": 74.0}, {"time": "2025-04-30", "open": 67.24, "high": 68.39, "low": 66.28, "close": 68.06, "rsi": 64.5}, {"time": "2025-05-01", "open": 67.83, "high": 68.95, "low": 67.16, "close": 68.41, "rsi": 83.3}, {"time": "2025-05-02", "open": 69.26, "high": 70.13, "low": 69.1, "close": 69.47, "rsi": 84.5}, {"time": "2025-05-05", "open": 68.92, "high": 69.2, "low": 68.21, "close": 68.61, "rsi": 72.0}, {"time": "2025-05-06", "open": 68.27, "high": 68.72, "low": 67.77, "close": 68.33, "rsi": 69.4}, {"time": "2025-05-07", "open": 68.38, "high": 68.81, "low": 68.11, "close": 68.35, "rsi": 69.4}, {"time": "2025-05-08", "open": 68.58, "high": 68.71, "low": 67.44, "close": 67.5, "rsi": 58.2}, {"time": "2025-05-09", "open": 67.57, "high": 67.96, "low": 67.3, "close": 67.75, "rsi": 64.8}, {"time": "2025-05-12", "open": 68.48, "high": 68.82, "low": 68.25, "close": 68.68, "rsi": 62.6}, {"time": "2025-05-13", "open": 68.55, "high": 68.79, "low": 67.11, "close": 67.41, "rsi": 51.2}, {"time": "2025-05-14", "open": 66.8, "high": 67.49, "low": 66.21, "close": 66.9, "rsi": 48.6}, {"time": "2025-05-15", "open": 67.12, "high": 68.73, "low": 67.04, "close": 68.64, "rsi": 61.5}, {"time": "2025-05-16", "open": 68.86, "high": 69.55, "low": 68.47, "close": 69.32, "rsi": 61.2}, {"time": "2025-05-19", "open": 68.61, "high": 69.28, "low": 68.37, "close": 69.11, "rsi": 59.1}, {"time": "2025-05-20", "open": 68.76, "high": 69.15, "low": 68.33, "close": 68.88, "rsi": 54.5}, {"time": "2025-05-21", "open": 68.54, "high": 68.75, "low": 66.75, "close": 66.77, "rsi": 42.6}, {"time": "2025-05-22", "open": 66.76, "high": 66.99, "low": 65.72, "close": 66.16, "rsi": 34.3}, {"time": "2025-05-23", "open": 65.85, "high": 66.29, "low": 64.85, "close": 65.49, "rsi": 35.0}, {"time": "2025-05-27", "open": 66.41, "high": 66.72, "low": 65.26, "close": 66.47, "rsi": 41.6}, {"time": "2025-05-28", "open": 66.54, "high": 66.96, "low": 66.03, "close": 66.85, "rsi": 43.4}, {"time": "2025-05-29", "open": 66.93, "high": 68.11, "low": 66.76, "close": 67.79, "rsi": 51.3}, {"time": "2025-05-30", "open": 67.33, "high": 68.1, "low": 66.99, "close": 67.94, "rsi": 50.8}, {"time": "2025-06-02", "open": 67.3, "high": 67.86, "low": 66.51, "close": 67.74, "rsi": 45.6}, {"time": "2025-06-03", "open": 67.36, "high": 67.55, "low": 66.12, "close": 66.74, "rsi": 46.8}, {"time": "2025-06-04", "open": 66.63, "high": 67.09, "low": 65.87, "close": 66.85, "rsi": 49.8}, {"time": "2025-06-05", "open": 66.86, "high": 66.97, "low": 66.16, "close": 66.32, "rsi": 36.8}, {"time": "2025-06-06", "open": 66.72, "high": 67.24, "low": 65.86, "close": 66.35, "rsi": 31.8}, {"time": "2025-06-09", "open": 66.11, "high": 67.67, "low": 66.07, "close": 67.15, "rsi": 38.8}, {"time": "2025-06-10", "open": 67.46, "high": 68.0, "low": 67.25, "close": 67.81, "rsi": 44.1}, {"time": "2025-06-11", "open": 68.01, "high": 68.01, "low": 66.65, "close": 67.1, "rsi": 52.1}, {"time": "2025-06-12", "open": 67.32, "high": 67.98, "low": 66.95, "close": 67.97, "rsi": 61.3}, {"time": "2025-06-13", "open": 67.35, "high": 67.96, "low": 66.15, "close": 66.72, "rsi": 57.1}, {"time": "2025-06-16", "open": 67.23, "high": 67.65, "low": 66.76, "close": 66.94, "rsi": 53.0}, {"time": "2025-06-17", "open": 67.21, "high": 67.21, "low": 66.3, "close": 66.58, "rsi": 48.3}, {"time": "2025-06-18", "open": 66.83, "high": 67.25, "low": 66.22, "close": 66.71, "rsi": 42.3}, {"time": "2025-06-20", "open": 66.81, "high": 67.24, "low": 66.38, "close": 66.83, "rsi": 42.0}, {"time": "2025-06-23", "open": 67.0, "high": 67.68, "low": 66.26, "close": 66.9, "rsi": 43.8}, {"time": "2025-06-24", "open": 66.9, "high": 67.27, "low": 65.83, "close": 66.09, "rsi": 45.1}, {"time": "2025-06-25", "open": 64.88, "high": 65.42, "low": 63.79, "close": 64.23, "rsi": 34.4}, {"time": "2025-06-26", "open": 64.58, "high": 66.02, "low": 64.13, "close": 66.01, "rsi": 48.4}, {"time": "2025-06-27", "open": 66.33, "high": 66.64, "low": 65.55, "close": 65.9, "rsi": 47.7}, {"time": "2025-06-30", "open": 65.74, "high": 66.09, "low": 64.82, "close": 66.04, "rsi": 43.9}, {"time": "2025-07-01", "open": 65.75, "high": 66.63, "low": 65.15, "close": 65.81, "rsi": 38.5}, {"time": "2025-07-02", "open": 65.45, "high": 65.91, "low": 64.45, "close": 65.24, "rsi": 39.0}, {"time": "2025-07-03", "open": 65.13, "high": 65.81, "low": 64.93, "close": 65.44, "rsi": 33.9}, {"time": "2025-07-07", "open": 65.79, "high": 66.53, "low": 64.88, "close": 65.28, "rsi": 39.4}, {"time": "2025-07-08", "open": 64.86, "high": 65.64, "low": 64.62, "close": 65.19, "rsi": 36.8}, {"time": "2025-07-09", "open": 65.19, "high": 65.63, "low": 65.0, "close": 65.1, "rsi": 38.4}, {"time": "2025-07-10", "open": 64.91, "high": 66.09, "low": 64.86, "close": 65.64, "rsi": 42.1}, {"time": "2025-07-11", "open": 64.86, "high": 65.57, "low": 64.69, "close": 65.35, "rsi": 39.4}, {"time": "2025-07-14", "open": 65.45, "high": 65.87, "low": 65.12, "close": 65.58, "rsi": 40.7}, {"time": "2025-07-15", "open": 65.42, "high": 65.53, "low": 64.3, "close": 64.71, "rsi": 40.4}, {"time": "2025-07-16", "open": 64.97, "high": 65.63, "low": 64.74, "close": 65.51, "rsi": 60.5}, {"time": "2025-07-17", "open": 65.61, "high": 66.04, "low": 65.39, "close": 65.83, "rsi": 48.1}, {"time": "2025-07-18", "open": 65.78, "high": 66.09, "low": 65.34, "close": 65.73, "rsi": 48.1}, {"time": "2025-07-21", "open": 65.78, "high": 66.11, "low": 65.18, "close": 65.54, "rsi": 44.7}, {"time": "2025-07-22", "open": 65.59, "high": 66.91, "low": 65.43, "close": 66.85, "rsi": 59.0}, {"time": "2025-07-23", "open": 66.91, "high": 67.04, "low": 66.43, "close": 66.87, "rsi": 65.7}, {"time": "2025-07-24", "open": 66.87, "high": 67.03, "low": 66.07, "close": 66.19, "rsi": 56.6}, {"time": "2025-07-25", "open": 66.17, "high": 66.61, "low": 65.64, "close": 65.92, "rsi": 55.5}, {"time": "2025-07-28", "open": 66.0, "high": 66.04, "low": 64.69, "close": 64.79, "rsi": 47.1}, {"time": "2025-07-29", "open": 65.11, "high": 66.37, "low": 64.86, "close": 66.32, "rsi": 57.4}, {"time": "2025-07-30", "open": 65.89, "high": 66.03, "low": 63.13, "close": 63.9, "rsi": 41.4}, {"time": "2025-07-31", "open": 63.55, "high": 63.7, "low": 61.63, "close": 61.84, "rsi": 35.3}, {"time": "2025-08-01", "open": 62.55, "high": 62.55, "low": 60.38, "close": 61.4, "rsi": 32.8}, {"time": "2025-08-04", "open": 61.37, "high": 62.27, "low": 61.18, "close": 61.32, "rsi": 35.1}, {"time": "2025-08-05", "open": 63.08, "high": 63.08, "low": 61.71, "close": 62.05, "rsi": 34.7}, {"time": "2025-08-06", "open": 62.17, "high": 62.64, "low": 61.75, "close": 62.04, "rsi": 32.7}, {"time": "2025-08-07", "open": 62.22, "high": 62.95, "low": 62.19, "close": 62.52, "rsi": 35.9}, {"time": "2025-08-08", "open": 62.63, "high": 62.72, "low": 61.74, "close": 61.84, "rsi": 34.4}, {"time": "2025-08-11", "open": 61.52, "high": 61.86, "low": 60.9, "close": 60.96, "rsi": 24.2}, {"time": "2025-08-12", "open": 60.98, "high": 61.37, "low": 60.75, "close": 61.35, "rsi": 26.6}, {"time": "2025-08-13", "open": 61.49, "high": 62.65, "low": 61.3, "close": 62.61, "rsi": 35.5}, {"time": "2025-08-14", "open": 62.0, "high": 62.33, "low": 61.83, "close": 62.14, "rsi": 35.0}, {"time": "2025-08-15", "open": 62.11, "high": 63.0, "low": 62.11, "close": 62.74, "rsi": 41.5}, {"time": "2025-08-18", "open": 62.89, "high": 63.06, "low": 61.83, "close": 61.88, "rsi": 30.4}, {"time": "2025-08-19", "open": 62.1, "high": 63.27, "low": 61.96, "close": 63.05, "rsi": 45.8}, {"time": "2025-08-20", "open": 63.37, "high": 63.96, "low": 62.91, "close": 63.09, "rsi": 57.7}, {"time": "2025-08-21", "open": 62.75, "high": 63.3, "low": 62.62, "close": 62.89, "rsi": 59.5}, {"time": "2025-08-22", "open": 63.3, "high": 64.29, "low": 63.09, "close": 63.86, "rsi": 64.5}, {"time": "2025-08-25", "open": 63.84, "high": 64.02, "low": 63.04, "close": 63.41, "rsi": 58.0}, {"time": "2025-08-26", "open": 63.54, "high": 63.8, "low": 62.95, "close": 63.09, "rsi": 56.0}, {"time": "2025-08-27", "open": 63.31, "high": 63.86, "low": 63.06, "close": 63.74, "rsi": 56.8}, {"time": "2025-08-28", "open": 64.02, "high": 64.02, "low": 63.28, "close": 63.89, "rsi": 62.2}, {"time": "2025-08-29", "open": 63.78, "high": 64.78, "low": 63.67, "close": 64.7, "rsi": 72.4}, {"time": "2025-09-02", "open": 64.25, "high": 64.29, "low": 62.28, "close": 62.63, "rsi": 56.4}, {"time": "2025-09-03", "open": 62.28, "high": 63.3, "low": 62.24, "close": 63.28, "rsi": 53.5}, {"time": "2025-09-04", "open": 63.6, "high": 64.21, "low": 63.35, "close": 64.18, "rsi": 60.4}, {"time": "2025-09-05", "open": 64.58, "high": 65.63, "low": 64.43, "close": 65.37, "rsi": 62.6}, {"time": "2025-09-08", "open": 64.8, "high": 65.23, "low": 64.39, "close": 64.96, "rsi": 65.5}, {"time": "2025-09-09", "open": 64.62, "high": 65.32, "low": 64.6, "close": 65.19, "rsi": 61.8}, {"time": "2025-09-10", "open": 65.19, "high": 65.68, "low": 64.32, "close": 64.44, "rsi": 56.9}, {"time": "2025-09-11", "open": 64.47, "high": 65.61, "low": 64.15, "close": 65.45, "rsi": 62.2}, {"time": "2025-09-12", "open": 65.48, "high": 65.67, "low": 64.96, "close": 65.01, "rsi": 55.8}, {"time": "2025-09-15", "open": 65.28, "high": 65.4, "low": 63.8, "close": 63.88, "rsi": 52.2}, {"time": "2025-09-16", "open": 63.75, "high": 64.08, "low": 63.23, "close": 63.36, "rsi": 51.2}, {"time": "2025-09-17", "open": 63.15, "high": 64.31, "low": 63.15, "close": 63.24, "rsi": 47.6}, {"time": "2025-09-18", "open": 63.45, "high": 63.68, "low": 62.91, "close": 63.47, "rsi": 48.0}, {"time": "2025-09-19", "open": 63.43, "high": 64.21, "low": 63.13, "close": 63.65, "rsi": 44.7}, {"time": "2025-09-22", "open": 63.52, "high": 63.93, "low": 63.0, "close": 63.89, "rsi": 57.8}, {"time": "2025-09-23", "open": 63.88, "high": 64.35, "low": 63.59, "close": 64.27, "rsi": 56.4}, {"time": "2025-09-24", "open": 64.06, "high": 64.31, "low": 63.44, "close": 63.76, "rsi": 47.1}, {"time": "2025-09-25", "open": 63.76, "high": 64.13, "low": 62.92, "close": 63.04, "rsi": 33.0}, {"time": "2025-09-26", "open": 63.31, "high": 64.13, "low": 63.02, "close": 63.82, "rsi": 42.1}, {"time": "2025-09-29", "open": 63.47, "high": 63.9, "low": 63.23, "close": 63.42, "rsi": 38.0}, {"time": "2025-09-30", "open": 63.21, "high": 64.06, "low": 63.14, "close": 64.02, "rsi": 47.1}, {"time": "2025-10-01", "open": 63.86, "high": 64.15, "low": 63.33, "close": 63.4, "rsi": 35.1}, {"time": "2025-10-02", "open": 63.14, "high": 63.3, "low": 62.42, "close": 62.78, "rsi": 34.2}, {"time": "2025-10-03", "open": 62.9, "high": 63.41, "low": 62.59, "close": 62.6, "rsi": 39.6}, {"time": "2025-10-06", "open": 62.65, "high": 62.73, "low": 61.5, "close": 61.54, "rsi": 36.3}, {"time": "2025-10-07", "open": 61.75, "high": 62.35, "low": 61.52, "close": 61.78, "rsi": 39.3}, {"time": "2025-10-08", "open": 61.4, "high": 61.73, "low": 61.25, "close": 61.64, "rsi": 36.3}, {"time": "2025-10-09", "open": 61.83, "high": 62.07, "low": 61.14, "close": 61.29, "rsi": 32.8}, {"time": "2025-10-10", "open": 61.43, "high": 61.81, "low": 60.42, "close": 60.99, "rsi": 29.1}, {"time": "2025-10-13", "open": 60.91, "high": 61.45, "low": 60.73, "close": 61.33, "rsi": 28.6}, {"time": "2025-10-14", "open": 61.28, "high": 61.66, "low": 61.04, "close": 61.62, "rsi": 33.9}, {"time": "2025-10-15", "open": 61.75, "high": 62.17, "low": 61.11, "close": 61.41, "rsi": 36.7}, {"time": "2025-10-16", "open": 61.62, "high": 61.62, "low": 60.49, "close": 60.82, "rsi": 24.8}, {"time": "2025-10-17", "open": 60.95, "high": 61.6, "low": 60.72, "close": 61.53, "rsi": 34.9}, {"time": "2025-10-20", "open": 61.93, "high": 62.29, "low": 61.53, "close": 61.66, "rsi": 29.6}, {"time": "2025-10-21", "open": 61.93, "high": 62.79, "low": 61.68, "close": 62.13, "rsi": 38.7}, {"time": "2025-10-22", "open": 62.4, "high": 63.19, "low": 61.88, "close": 63.04, "rsi": 52.2}, {"time": "2025-10-23", "open": 63.19, "high": 63.24, "low": 62.13, "close": 62.63, "rsi": 50.2}, {"time": "2025-10-24", "open": 63.02, "high": 63.08, "low": 62.48, "close": 62.72, "rsi": 61.5}, {"time": "2025-10-27", "open": 62.65, "high": 62.81, "low": 61.9, "close": 62.61, "rsi": 58.3}, {"time": "2025-10-28", "open": 62.35, "high": 62.83, "low": 60.76, "close": 60.78, "rsi": 43.6}, {"time": "2025-10-29", "open": 59.24, "high": 60.03, "low": 57.87, "close": 58.26, "rsi": 33.0}, {"time": "2025-10-30", "open": 58.35, "high": 59.83, "low": 57.96, "close": 59.65, "rsi": 43.3}, {"time": "2025-10-31", "open": 59.45, "high": 60.03, "low": 58.76, "close": 58.79, "rsi": 37.9}, {"time": "2025-11-03", "open": 58.11, "high": 59.4, "low": 57.74, "close": 58.43, "rsi": 34.9}, {"time": "2025-11-04", "open": 58.28, "high": 58.81, "low": 57.83, "close": 58.73, "rsi": 37.4}, {"time": "2025-11-05", "open": 59.02, "high": 59.26, "low": 58.15, "close": 59.11, "rsi": 41.8}, {"time": "2025-11-06", "open": 59.04, "high": 59.24, "low": 58.01, "close": 58.05, "rsi": 33.9}, {"time": "2025-11-07", "open": 58.38, "high": 59.13, "low": 58.24, "close": 59.05, "rsi": 38.8}, {"time": "2025-11-10", "open": 58.97, "high": 59.1, "low": 58.14, "close": 58.86, "rsi": 35.6}, {"time": "2025-11-11", "open": 59.19, "high": 59.9, "low": 58.95, "close": 59.83, "rsi": 36.0}, {"time": "2025-11-12", "open": 59.41, "high": 59.9, "low": 58.92, "close": 58.96, "rsi": 34.6}, {"time": "2025-11-13", "open": 58.51, "high": 59.16, "low": 58.41, "close": 58.63, "rsi": 33.2}, {"time": "2025-11-14", "open": 58.97, "high": 59.36, "low": 58.6, "close": 58.77, "rsi": 34.2}, {"time": "2025-11-17", "open": 59.0, "high": 59.06, "low": 58.2, "close": 58.4, "rsi": 38.9}, {"time": "2025-11-18", "open": 58.43, "high": 58.88, "low": 58.15, "close": 58.53, "rsi": 51.6}, {"time": "2025-11-19", "open": 58.5, "high": 58.56, "low": 58.02, "close": 58.29, "rsi": 40.6}, {"time": "2025-11-20", "open": 58.73, "high": 59.28, "low": 58.35, "close": 58.51, "rsi": 47.9}, {"time": "2025-11-21", "open": 58.76, "high": 60.19, "low": 58.74, "close": 59.88, "rsi": 59.6}, {"time": "2025-11-24", "open": 59.6, "high": 60.24, "low": 59.3, "close": 59.88, "rsi": 58.0}, {"time": "2025-11-25", "open": 60.15, "high": 60.96, "low": 60.11, "close": 60.43, "rsi": 58.9}, {"time": "2025-11-26", "open": 60.22, "high": 61.27, "low": 60.17, "close": 60.9, "rsi": 70.8}, {"time": "2025-11-28", "open": 60.82, "high": 61.36, "low": 60.77, "close": 61.07, "rsi": 66.8}, {"time": "2025-12-01", "open": 60.61, "high": 61.45, "low": 60.35, "close": 60.76, "rsi": 65.6}, {"time": "2025-12-02", "open": 60.98, "high": 61.48, "low": 60.43, "close": 61.3, "rsi": 63.0}, {"time": "2025-12-03", "open": 61.19, "high": 61.62, "low": 61.09, "close": 61.35, "rsi": 74.4}, {"time": "2025-12-04", "open": 61.22, "high": 61.73, "low": 60.82, "close": 60.93, "rsi": 73.3}, {"time": "2025-12-05", "open": 60.71, "high": 61.16, "low": 60.31, "close": 60.39, "rsi": 65.1}, {"time": "2025-12-08", "open": 60.54, "high": 60.58, "low": 59.36, "close": 59.93, "rsi": 64.1}, {"time": "2025-12-09", "open": 60.24, "high": 60.76, "low": 59.35, "close": 59.39, "rsi": 57.3}, {"time": "2025-12-10", "open": 59.41, "high": 60.45, "low": 59.41, "close": 60.0, "rsi": 63.7}, {"time": "2025-12-11", "open": 60.19, "high": 60.72, "low": 59.76, "close": 59.96, "rsi": 62.0}, {"time": "2025-12-12", "open": 60.23, "high": 60.55, "low": 59.94, "close": 60.28, "rsi": 54.0}, {"time": "2025-12-15", "open": 60.48, "high": 60.62, "low": 60.06, "close": 60.43, "rsi": 55.3}, {"time": "2025-12-16", "open": 60.59, "high": 60.63, "low": 59.81, "close": 60.06, "rsi": 46.3}, {"time": "2025-12-17", "open": 60.29, "high": 61.59, "low": 60.11, "close": 61.3, "rsi": 53.4}, {"time": "2025-12-18", "open": 61.31, "high": 61.95, "low": 61.08, "close": 61.41, "rsi": 53.0}, {"time": "2025-12-19", "open": 61.58, "high": 61.58, "low": 60.69, "close": 60.7, "rsi": 49.4}, {"time": "2025-12-22", "open": 60.52, "high": 61.83, "low": 60.22, "close": 61.61, "rsi": 52.4}, {"time": "2025-12-23", "open": 61.76, "high": 61.76, "low": 60.99, "close": 61.64, "rsi": 52.3}, {"time": "2025-12-24", "open": 61.9, "high": 62.3, "low": 61.66, "close": 62.04, "rsi": 58.6}, {"time": "2025-12-26", "open": 62.01, "high": 62.45, "low": 61.91, "close": 62.4, "rsi": 66.1}, {"time": "2025-12-29", "open": 62.55, "high": 62.61, "low": 62.18, "close": 62.58, "rsi": 72.2}, {"time": "2025-12-30", "open": 63.18, "high": 63.49, "low": 62.42, "close": 62.8, "rsi": 80.2}, {"time": "2025-12-31", "open": 62.8, "high": 62.95, "low": 62.31, "close": 62.35, "rsi": 71.4}, {"time": "2026-01-02", "open": 62.32, "high": 62.34, "low": 61.57, "close": 62.03, "rsi": 67.9}, {"time": "2026-01-05", "open": 61.56, "high": 61.88, "low": 60.89, "close": 60.92, "rsi": 54.9}, {"time": "2026-01-06", "open": 60.67, "high": 62.56, "low": 60.55, "close": 62.41, "rsi": 62.5}, {"time": "2026-01-07", "open": 62.55, "high": 63.0, "low": 61.9, "close": 61.94, "rsi": 61.7}, {"time": "2026-01-08", "open": 61.69, "high": 63.39, "low": 61.69, "close": 62.87, "rsi": 60.2}, {"time": "2026-01-09", "open": 62.36, "high": 62.87, "low": 60.11, "close": 60.44, "rsi": 45.2}, {"time": "2026-01-12", "open": 60.56, "high": 60.88, "low": 60.08, "close": 60.26, "rsi": 47.7}, {"time": "2026-01-13", "open": 60.36, "high": 60.62, "low": 59.1, "close": 60.19, "rsi": 41.8}, {"time": "2026-01-14", "open": 60.15, "high": 61.31, "low": 60.15, "close": 61.2, "rsi": 47.7}, {"time": "2026-01-15", "open": 61.32, "high": 61.9, "low": 61.09, "close": 61.17, "rsi": 45.3}, {"time": "2026-01-16", "open": 60.92, "high": 62.12, "low": 60.31, "close": 62.04, "rsi": 48.2}, {"time": "2026-01-20", "open": 61.2, "high": 61.59, "low": 60.58, "close": 61.02, "rsi": 42.6}, {"time": "2026-01-21", "open": 61.13, "high": 61.57, "low": 60.78, "close": 61.35, "rsi": 43.2}, {"time": "2026-01-22", "open": 61.31, "high": 61.78, "low": 60.63, "close": 60.96, "rsi": 43.5}, {"time": "2026-01-23", "open": 60.91, "high": 62.14, "low": 60.7, "close": 62.09, "rsi": 50.3}, {"time": "2026-01-26", "open": 62.41, "high": 62.5, "low": 61.48, "close": 62.12, "rsi": 55.8}, {"time": "2026-01-27", "open": 62.23, "high": 62.66, "low": 61.99, "close": 62.15, "rsi": 48.5}, {"time": "2026-01-28", "open": 62.17, "high": 62.46, "low": 60.61, "close": 60.76, "rsi": 44.0}, {"time": "2026-01-29", "open": 61.21, "high": 62.01, "low": 60.93, "close": 61.86, "rsi": 45.0}], "signals": [{"ticker": "EQR", "date": "2023-10-02", "price": 52.84, "rsi": 18.9, "type": "oversold", "forward_return": 8.55}, {"ticker": "EQR", "date": "2023-10-03", "price": 52.22, "rsi": 18.8, "type": "oversold", "forward_return": 7.2}, {"ticker": "EQR", "date": "2023-11-01", "price": 48.57, "rsi": 19.3, "type": "oversold", "forward_return": 14.34}, {"ticker": "EQR", "date": "2024-10-03", "price": 69.69, "rsi": 19.9, "type": "oversold", "forward_return": -2.41}, {"ticker": "EQR", "date": "2024-12-18", "price": 66.7, "rsi": 15.0, "type": "oversold", "forward_return": 2.63}, {"ticker": "EQR", "date": "2024-12-19", "price": 66.03, "rsi": 15.2, "type": "oversold", "forward_return": 3.19}, {"ticker": "EQR", "date": "2023-04-13", "price": 53.66, "rsi": 82.8, "type": "overbought", "forward_return": 15.3}, {"ticker": "EQR", "date": "2023-04-17", "price": 54.8, "rsi": 82.6, "type": "overbought", "forward_return": 11.0}, {"ticker": "EQR", "date": "2023-04-18", "price": 54.9, "rsi": 85.6, "type": "overbought", "forward_return": 11.95}, {"ticker": "EQR", "date": "2023-04-19", "price": 55.5, "rsi": 83.5, "type": "overbought", "forward_return": 11.57}, {"ticker": "EQR", "date": "2023-06-14", "price": 59.31, "rsi": 91.5, "type": "overbought", "forward_return": -3.77}, {"ticker": "EQR", "date": "2023-06-15", "price": 59.3, "rsi": 93.1, "type": "overbought", "forward_return": -3.81}, {"ticker": "EQR", "date": "2023-06-16", "price": 59.63, "rsi": 93.3, "type": "overbought", "forward_return": -5.76}, {"ticker": "EQR", "date": "2023-06-20", "price": 59.02, "rsi": 85.5, "type": "overbought", "forward_return": -5.05}, {"ticker": "EQR", "date": "2023-07-14", "price": 61.87, "rsi": 87.3, "type": "overbought", "forward_return": -11.02}, {"ticker": "EQR", "date": "2023-12-14", "price": 56.89, "rsi": 80.0, "type": "overbought", "forward_return": 1.19}, {"ticker": "EQR", "date": "2024-05-06", "price": 62.24, "rsi": 86.8, "type": "overbought", "forward_return": 8.1}, {"ticker": "EQR", "date": "2024-05-07", "price": 62.22, "rsi": 85.5, "type": "overbought", "forward_return": 6.04}, {"ticker": "EQR", "date": "2024-06-18", "price": 63.26, "rsi": 82.7, "type": "overbought", "forward_return": 14.77}, {"ticker": "EQR", "date": "2024-06-20", "price": 63.29, "rsi": 81.4, "type": "overbought", "forward_return": 14.69}, {"ticker": "EQR", "date": "2024-06-24", "price": 64.54, "rsi": 80.9, "type": "overbought", "forward_return": 13.02}, {"ticker": "EQR", "date": "2024-08-28", "price": 69.88, "rsi": 80.6, "type": "overbought", "forward_return": 4.84}, {"ticker": "EQR", "date": "2024-08-30", "price": 70.53, "rsi": 85.2, "type": "overbought", "forward_return": 3.28}, {"ticker": "EQR", "date": "2024-09-03", "price": 71.27, "rsi": 86.3, "type": "overbought", "forward_return": 0.32}, {"ticker": "EQR", "date": "2024-09-04", "price": 71.1, "rsi": 83.8, "type": "overbought", "forward_return": -1.06}, {"ticker": "EQR", "date": "2024-09-05", "price": 71.02, "rsi": 82.6, "type": "overbought", "forward_return": -1.27}, {"ticker": "EQR", "date": "2025-03-03", "price": 71.96, "rsi": 82.0, "type": "overbought", "forward_return": -5.87}, {"ticker": "EQR", "date": "2025-05-01", "price": 68.41, "rsi": 83.3, "type": "overbought", "forward_return": -10.24}, {"ticker": "EQR", "date": "2025-05-02", "price": 69.47, "rsi": 84.5, "type": "overbought", "forward_return": -11.73}, {"ticker": "EQR", "date": "2025-12-30", "price": 62.8, "rsi": 80.2, "type": "overbought"}]}